shakespearelang/__init__.py
shakespearelang/_character.py
shakespearelang/_expression.py
shakespearelang/_input.py
shakespearelang/_operation.py
shakespearelang/_output.py
shakespearelang/_parser.py
shakespearelang/_preprocess.py
shakespearelang/_repl.py
shakespearelang/_state.py
shakespearelang/_utils.py
shakespearelang/cli.py
shakespearelang/errors.py
shakespearelang/settings.py
shakespearelang/shakespeare.ebnf
shakespearelang/shakespeare.py
shakespearelang/tests/__init__.py
shakespearelang/tests/sample_plays/catch.spl
shakespearelang/tests/sample_plays/echo.spl
shakespearelang/tests/sample_plays/hello_world.spl
shakespearelang/tests/sample_plays/hi.spl
shakespearelang/tests/sample_plays/parse_everything.spl
shakespearelang/tests/sample_plays/primes.spl
shakespearelang/tests/sample_plays/reverse.spl
shakespearelang/tests/sample_plays/sierpinski.spl
shakespearelang/tests/test_assignment.py
shakespearelang/tests/test_character_input.py
shakespearelang/tests/test_character_output.py
shakespearelang/tests/test_console.py
shakespearelang/tests/test_debugging.py
shakespearelang/tests/test_dramatis_personae.py
shakespearelang/tests/test_enter_and_exit.py
shakespearelang/tests/test_expressions.py
shakespearelang/tests/test_gotos.py
shakespearelang/tests/test_input_styles.py
shakespearelang/tests/test_numeric_input.py
shakespearelang/tests/test_numeric_output.py
shakespearelang/tests/test_output_styles.py
shakespearelang/tests/test_parse_error_format.py
shakespearelang/tests/test_runtime_error_format.py
shakespearelang/tests/test_sample_plays.py
shakespearelang/tests/test_stacks.py
shakespearelang/tests/utils.py
shakespearelang-1.0.0.dist-info/LICENSE
shakespearelang-1.0.0.dist-info/METADATA
shakespearelang-1.0.0.dist-info/WHEEL
shakespearelang-1.0.0.dist-info/entry_points.txt
shakespearelang-1.0.0.dist-info/RECORD
