Metadata-Version: 2.1
Name: shakespearelang
Version: 1.0.0
Summary: An interpreter for the Shakespeare Programming Language.
Home-page: http://shakespearelang.com
License: MIT
Author: Zeb Burke-Conte
Author-email: zebburkeconte@gmail.com
Requires-Python: >=3.8,<4.0
Classifier: Development Status :: 5 - Production/Stable
Classifier: License :: OSI Approved :: MIT License
Classifier: Programming Language :: Python :: 3
Classifier: Programming Language :: Python :: 3.8
Classifier: Programming Language :: Python :: 3.9
Classifier: Programming Language :: Python :: 3.10
Classifier: Programming Language :: Python :: 3.11
Classifier: Programming Language :: Python :: 3.12
Classifier: Topic :: Software Development :: Interpreters
Requires-Dist: click (>=7.1.2,<8.0.0)
Requires-Dist: tatsu (>=5.6.1,<5.7.0)
Project-URL: Repository, http://github.com/zmbc/shakespearelang
